dci_downloader/__init__.py
dci_downloader/api.py
dci_downloader/cli.py
dci_downloader/containers.py
dci_downloader/downloader.py
dci_downloader/files_list.py
dci_downloader/filters.py
dci_downloader/fs.py
dci_downloader/lock.py
dci_downloader/main.py
dci_downloader/settings.py
dci_downloader/stats.py
dci_downloader/version.py
dci_downloader-3.2.0.post202510211612.dist-info/LICENSE
dci_downloader-3.2.0.post202510211612.dist-info/METADATA
dci_downloader-3.2.0.post202510211612.dist-info/WHEEL
dci_downloader-3.2.0.post202510211612.dist-info/entry_points.txt
dci_downloader-3.2.0.post202510211612.dist-info/top_level.txt
dci_downloader-3.2.0.post202510211612.dist-info/RECORD
