Metadata-Version: 2.1
Name: dci-downloader
Version: 3.2.0.post202510211612
Summary: DCI downloader module
Home-page: https://github.com/redhat-cip/dci-downloader
Author: Distributed CI team
Author-email: distributed-ci@redhat.com
License: Apache v2.0
Classifier: License :: OSI Approved :: Apache Software License
Classifier: Operating System :: POSIX :: Linux
Classifier: Programming Language :: Python :: 2
Classifier: Programming Language :: Python :: 3
License-File: LICENSE
Requires-Dist: requests
Requires-Dist: dciclient
Requires-Dist: PyYAML
Requires-Dist: dciauth
Requires-Dist: futures ; python_version == "2.7"
